segypy/__init__.py
segypy/segypy.py
segypy-0.60.dist-info/licenses/LICENSE.txt
temp_wheel_inspect/segypy/__init__.py
temp_wheel_inspect/segypy/segypy.py
temp_wheel_inspect/temp_wheel_inspect/segypy/__init__.py
temp_wheel_inspect/temp_wheel_inspect/segypy/segypy.py
segypy-0.60.dist-info/METADATA
segypy-0.60.dist-info/WHEEL
segypy-0.60.dist-info/top_level.txt
segypy-0.60.dist-info/RECORD
