Metadata-Version: 2.4
Name: segypy
Version: 0.60
Summary: Reading and writing SEGY formatted files
Author-email: Thomas Mejer Hansen <thomas.mejer.hansen@gmail.com>
License: Copyright 2018 Thomas Mejer Hansen
Project-URL: Homepage, https://github.com/cultpenguin/segypy
Project-URL: Download, https://github.com/cultpenguin/segypy/archive/master.zip
Keywords: segy,reading,writing
Classifier: Development Status :: 4 - Beta
Classifier: Programming Language :: Python :: 3.7
Classifier: Programming Language :: Python :: 3.8
Classifier: Programming Language :: Python :: 3.9
Classifier: Programming Language :: Python :: 3.10
Classifier: Programming Language :: Python :: 3.11
Classifier: Programming Language :: Python :: 3 :: Only
Requires-Python: >=3.7
License-File: LICENSE.txt
Requires-Dist: numpy>=1.19.0
Dynamic: license-file
